evchargingfinderlib/__init__.py
evchargingfinderlib/booking.py
evchargingfinderlib-0.1.0.dist-info/LICENCE.txt
evchargingfinderlib-0.1.0.dist-info/METADATA
evchargingfinderlib-0.1.0.dist-info/WHEEL
evchargingfinderlib-0.1.0.dist-info/top_level.txt
evchargingfinderlib-0.1.0.dist-info/RECORD
